tests/__init__.py
tests/test_timespy.py
timespy/__init__.py
timespy/timespy.py
timespy-1.0.0.dist-info/LICENSE
timespy-1.0.0.dist-info/METADATA
timespy-1.0.0.dist-info/WHEEL
timespy-1.0.0.dist-info/top_level.txt
timespy-1.0.0.dist-info/RECORD
